procrunner/__init__.py
procrunner-2.3.3.dist-info/LICENSE
procrunner-2.3.3.dist-info/METADATA
procrunner-2.3.3.dist-info/WHEEL
procrunner-2.3.3.dist-info/top_level.txt
procrunner-2.3.3.dist-info/RECORD
