Metadata-Version: 2.1
Name: procrunner
Version: 2.3.3
Summary: Versatile utility function to run external processes
Home-page: https://github.com/DiamondLightSource/python-procrunner
Author: Markus Gerstel
Author-email: scientificsoftware@diamond.ac.uk
License: BSD
Project-URL: Download, https://github.com/DiamondLightSource/python-procrunner/tags
Project-URL: Documentation, https://procrunner.readthedocs.io/
Project-URL: GitHub, https://github.com/DiamondLightSource/python-procrunner
Project-URL: Bug-Tracker, https://github.com/DiamondLightSource/python-procrunner/issues
Keywords: procrunner
Platform: UNKNOWN
Classifier: Development Status :: 5 - Production/Stable
Classifier: Intended Audience :: Developers
Classifier: License :: OSI Approved :: BSD License
Classifier: Natural Language :: English
Classifier: Programming Language :: Python :: 3
Classifier: Programming Language :: Python :: 3.6
Classifier: Programming Language :: Python :: 3.7
Classifier: Programming Language :: Python :: 3.8
Classifier: Programming Language :: Python :: 3.9
Classifier: Programming Language :: Python :: 3.10
Classifier: Operating System :: OS Independent
Classifier: Topic :: Software Development :: Libraries :: Python Modules
Requires-Python: >=3.6
License-File: LICENSE
